credspray_wrapper.py
credspray-1.0.2.dist-info/licenses/LICENSE
credspray-1.0.2.dist-info/METADATA
credspray-1.0.2.dist-info/WHEEL
credspray-1.0.2.dist-info/entry_points.txt
credspray-1.0.2.dist-info/top_level.txt
credspray-1.0.2.dist-info/RECORD
