Metadata-Version: 2.4
Name: credspray
Version: 1.0.2
Summary: Multi-protocol credential validation tool for penetration testing
Author: Strikoder
License: MIT
Project-URL: Homepage, https://github.com/strikoder/CredSpray
Project-URL: Repository, https://github.com/strikoder/CredSpray
Project-URL: Issues, https://github.com/strikoder/CredSpray/issues
Project-URL: Documentation, https://github.com/strikoder/CredSpray#readme
Keywords: penetration-testing,security,credentials,netexec,oscp,ctf,password-spraying
Classifier: Development Status :: 5 - Production/Stable
Classifier: Intended Audience :: Information Technology
Classifier: Topic :: Security
Classifier: License :: OSI Approved :: MIT License
Classifier: Programming Language :: Python :: 3
Classifier: Programming Language :: Python :: 3.7
Classifier: Programming Language :: Python :: 3.8
Classifier: Programming Language :: Python :: 3.9
Classifier: Programming Language :: Python :: 3.10
Classifier: Programming Language :: Python :: 3.11
Classifier: Programming Language :: Python :: 3.12
Requires-Python: >=3.7
License-File: LICENSE
Dynamic: license-file
